{
  "db_name": "PostgreSQL",
  "query": "UPDATE player_units SET current_level = $1, current_xp = $2, current_attack = current_attack + $3, current_defense = current_defense + $4, current_health = current_health + $5 WHERE player_unit_id = $6",
  "describe": {
    "columns": [],
    "parameters": {
      "Left": [
        "Int4",
        "Int4",
        "Int4",
        "Int4",
        "Int4",
        "Int4"
      ]
    },
    "nullable": []
  },
  "hash": "7ed49380156be865d85547436e8db31bf7ef5e45e529008c0fa852e509851f02"
}
